scrappi/__init__.py
scrappi/_version.py
scrappi/submodule_template/__init__.py
scrappi/submodule_template/class_template.py
scrappi/submodule_template/tests/__init__.py
scrappi/submodule_template/tests/test_class_template.py
scrappi-0.0.dist-info/METADATA
scrappi-0.0.dist-info/WHEEL
scrappi-0.0.dist-info/top_level.txt
scrappi-0.0.dist-info/RECORD
