Metadata-Version: 2.1
Name: scrappi
Version: 0.0
Summary: EO Satellite product catalogue retrieval by API or file system
Home-page: https://gitlab.npl.co.uk/eco/tools/scrappi
Author: Sam Hunt
Author-email: sam.hunt@npl.co.uk
License: None
Classifier: Development Status :: 2 - Pre-Alpha
Classifier: Programming Language :: Python
Classifier: Programming Language :: Python :: 3.6
Classifier: Programming Language :: Python :: 3.7
Classifier: Programming Language :: Python :: 3.8
Provides-Extra: dev
Requires-Dist: pre-commit ; extra == 'dev'
Requires-Dist: tox ; extra == 'dev'
Requires-Dist: sphinx ; extra == 'dev'
Requires-Dist: sphinx-rtd-theme ; extra == 'dev'
